django_graphene_filters/__init__.py
django_graphene_filters/conf.py
django_graphene_filters/connection_field.py
django_graphene_filters/filter_arguments_factory.py
django_graphene_filters/filters.py
django_graphene_filters/filterset.py
django_graphene_filters/filterset_factories.py
django_graphene_filters/input_data_factories.py
django_graphene_filters/input_types.py
django_graphene_filters/utils.py
django_graphene_filters-0.0.8.dist-info/LICENSE
django_graphene_filters-0.0.8.dist-info/METADATA
django_graphene_filters-0.0.8.dist-info/WHEEL
django_graphene_filters-0.0.8.dist-info/RECORD
