Metadata-Version: 2.1
Name: django-graphene-filters
Version: 0.0.8
Summary: Advanced auto related filters for Graphene Django
Home-page: https://github.com/riodw/django-graphene-filters
Keywords: django,graphene,filters,related
Author: Rio Weber
Author-email: riodweber@gmail.com
Maintainer: Rio Weber
Maintainer-email: riodweber@gmail.com
Requires-Python: >=3.9,<4.0
Classifier: Framework :: Django
Classifier: Operating System :: OS Independent
Classifier: Programming Language :: Python :: 3
Classifier: Programming Language :: Python :: 3.9
Classifier: Programming Language :: Python :: 3.10
Classifier: Programming Language :: Python :: 3.11
Requires-Dist: anytree (>=2.8.0,<3.0.0)
Requires-Dist: django (>=4.2.9,<5.0.0)
Requires-Dist: django-filter (>=23.2,<24.0)
Requires-Dist: graphene (>=2.1.9,<4)
Requires-Dist: graphene-django (>=3.0.0,<4.0.0)
Requires-Dist: psycopg2-binary (>=2.9.3,<3.0.0)
Requires-Dist: stringcase (>=1.2.0,<2.0.0)
Requires-Dist: wrapt (>=1.14.0,<2.0.0)
Project-URL: Repository, https://github.com/riodw/django-graphene-filters
